PyQt5/Qt5/lib/libQt5Purchasing.so.5
PyQt5/Qt5/qml/QtPurchasing/libdeclarative_purchasing.so
PyQt5/Qt5/qml/QtPurchasing/plugins.qmltypes
PyQt5/Qt5/qml/QtPurchasing/qmldir
pyqtpurchasing_qt5-5.15.18.dist-info/LICENSE
pyqtpurchasing_qt5-5.15.18.dist-info/METADATA
pyqtpurchasing_qt5-5.15.18.dist-info/WHEEL
pyqtpurchasing_qt5-5.15.18.dist-info/RECORD
